apistar/__init__.py
apistar/exceptions.py
arkindex/__init__.py
arkindex/auth.py
arkindex/compat.py
arkindex/document.py
arkindex/exceptions.py
arkindex/mock.py
arkindex/pagination.py
arkindex/client/__init__.py
arkindex/client/client.py
arkindex/client/decoders.py
arkindex/schema/__init__.py
arkindex/schema/openapi.py
arkindex/schema/validator.py
arkindex_client-1.1.5.dist-info/LICENSE
arkindex_client-1.1.5.dist-info/METADATA
arkindex_client-1.1.5.dist-info/WHEEL
arkindex_client-1.1.5.dist-info/top_level.txt
arkindex_client-1.1.5.dist-info/RECORD
